__init__.py
pybaseanal.py
pybaseanal-0.1.2.dist-info/LICENSE
pybaseanal-0.1.2.dist-info/METADATA
pybaseanal-0.1.2.dist-info/WHEEL
pybaseanal-0.1.2.dist-info/top_level.txt
pybaseanal-0.1.2.dist-info/RECORD
