Metadata-Version: 2.1
Name: pybaseanal
Version: 0.1.2
Summary: A package to import basic libraries and perform basic data analysis.
Author-email: Ateendra Jha <ajha@phaf.in>
Project-URL: Homepage, https://www.drateendrajha.com/projects/pybaseanal
Project-URL: Issues, https://www.drateendrajha.com/projects/pybaseanal
Keywords: python,pandas,numpy,basic libraries,Null analysis
Classifier: Programming Language :: Python :: 3
Classifier: License :: OSI Approved :: MIT License
Classifier: Operating System :: OS Independent
Requires-Python: >=3.6
License-File: LICENSE
Requires-Dist: pandas
Requires-Dist: numpy
Requires-Dist: seaborn
Requires-Dist: matplotlib
Requires-Dist: docx
Requires-Dist: tqdm
